LICENSE
sushitools/__init__.py
sushitools/cf/__init__.py
sushitools/cf/match.py
sushitools/classes.py
sushitools/decorators.py
sushitools/extension.py
sushitools/json.py
sushitools/primitive.py
sushitools/properties.py
sushitools/types/__init__.py
sushitools/types/dataenum.py
sushitools/types/object.py
sushitools-0.1.5.dist-info/LICENSE
sushitools-0.1.5.dist-info/METADATA
sushitools-0.1.5.dist-info/WHEEL
sushitools-0.1.5.dist-info/RECORD
