Metadata-Version: 2.1
Name: sushitools
Version: 0.1.5
Summary: python package with various different utilities and tools to make life easier.
Home-page: https://github.com/Dmunch04/sushitools
License: MIT
Keywords: tools,tool
Author: munchii
Author-email: daniellmunch@gmail.com
Requires-Python: >=3.12,<4.0
Classifier: Development Status :: 2 - Pre-Alpha
Classifier: Intended Audience :: Developers
Classifier: License :: OSI Approved :: MIT License
Classifier: Operating System :: OS Independent
Classifier: Programming Language :: Python :: 3
Classifier: Programming Language :: Python :: 3.12
Classifier: Topic :: Software Development :: Libraries
Classifier: Topic :: Utilities
Classifier: Typing :: Typed
Requires-Dist: numpy (>=1.23.3,<2.0.0)
Project-URL: Repository, https://github.com/Dmunch04/sushitools
